UCS614/q11.v
module JKFlipFlop(jk, q, qbar, clk);
	input [1:0] jk;
	input clk;
	output q, qbar;
	reg q, qbar;

	initial	begin
		q = 0;
		qbar = ~q;
	end

	always @(posedge clk) begin
		case(jk)
			2'b00:	q = q;
			2'b01:	q = 1'b0;
			2'b10:	q = 1'b1;
			2'b11:	q = ~q;
		endcase
		qbar = ~q;
	end
endmodule

module test;
	reg [1:0] jk;
	reg clk, i;
	wire q, qbar;
	JKFlipFlop t(jk,q,qbar,clk);

	initial begin
		clk = 1'b0;
		for (i = 0; i < 8; i++)
			#5 clk = ~clk;
	end

	initial begin
		$dumpfile("q11.vcd");
		$dumpvars(0,test);
		$display("CLK\tS\tR\tQ\tQbar");
		$monitor("%b\t%b\t%b\t%b\t%b", clk, jk[1], jk[0], q, qbar);
		jk = 2'b00; #10
		jk = 2'b01; #10
		jk = 2'b10; #10
		jk = 2'b11; #10 $finish;
	end
endmodule

UCS614/q11.vcd
$date
	Wed Mar 21 11:34:26 2018
$end
$version
	Icarus Verilog
$end
$timescale
	1s
$end
$scope module test $end
$var wire 1 ! qbar $end
$var wire 1 " q $end
$var reg 1 # clk $end
$var reg 1 $ i $end
$var reg 2 % jk [1:0] $end
$scope module t $end
$var wire 1 # clk $end
$var wire 2 & jk [1:0] $end
$var reg 1 " q $end
$var reg 1 ! qbar $end
$upscope $end
$upscope $end
$enddefinitions $end
#0
$dumpvars
b0 &
b0 %
0$
0#
0"
1!
$end
#5
1$
1#
#10
0$
0#
b1 %
b1 &
#15
1$
1#
#20
0$
0#
b10 %
b10 &
#25
0!
1"
1$
1#
#30
0$
0#
b11 %
b11 &
#35
1!
0"
1$
1#
#40
0$
0#
