UCS614/q12.v
module DFlipFlop(d, q, qbar, clk);
	input d, clk;
	output q, qbar;
	reg q, qbar;

	initial	begin
		q = 0;
		qbar = ~q;
	end

	always @(posedge clk) begin
		case(d)
			1'b0:	q = 1'b0;
			1'b1:	q = 1'b1;
		endcase
		qbar = ~q;
	end
endmodule

module test;
	reg d, clk, i;
	wire q, qbar;
	DFlipFlop t(d,q,qbar,clk);

	initial begin
		clk = 1'b0;
		for (i = 0; i < 8; i++) begin
			#5 clk = ~clk;
		end
	end

	initial begin
		$dumpfile("q12.vcd");
		$dumpvars(0,test);
		$display("CLK\tD\tQ\tQbar");
		$monitor("%b\t%b\t%b\t%b", clk, d, q, qbar);
		d = 1'b0; #10
		d = 1'b1; #10
 		d = 1'b0; #10
		d = 1'b1; #10 $finish;
	end
endmodule

UCS614/q12.vcd
$date
	Wed Mar 21 11:34:31 2018
$end
$version
	Icarus Verilog
$end
$timescale
	1s
$end
$scope module test $end
$var wire 1 ! qbar $end
$var wire 1 " q $end
$var reg 1 # clk $end
$var reg 1 $ d $end
$var reg 1 % i $end
$scope module t $end
$var wire 1 # clk $end
$var wire 1 $ d $end
$var reg 1 " q $end
$var reg 1 ! qbar $end
$upscope $end
$upscope $end
$enddefinitions $end
#0
$dumpvars
0%
0$
0#
0"
1!
$end
#5
1%
1#
#10
0%
0#
1$
#15
0!
1"
1%
1#
#20
0%
0#
0$
#25
1!
0"
1%
1#
#30
0%
0#
1$
#35
0!
1"
1%
1#
#40
0%
0#
