UCS614/q13.v
module TFlipFlop(t, q, qbar, clk);
	input t, clk;
	output q, qbar;
	reg q, qbar;

	initial	begin
		q = 0;
		qbar = ~q;
	end

	always @(posedge clk) begin
		case(t)
			1'b0:	q = q;
			1'b1:	q = ~q;
		endcase
		qbar = ~q;
	end
endmodule

module test;
	reg t, clk, i;
	wire q, qbar;
	TFlipFlop tff(t,q,qbar,clk);

	initial begin
		clk = 1'b0;
		for (i = 0; i < 8; i++)
			#5 clk = ~clk;
	end

	initial begin
		$dumpfile("q13.vcd");
		$dumpvars(0,test);
		$display("CLK\tT\tQ\tQbar");
		$monitor("%b\t%b\t%b\t%b", clk, t, q, qbar);
		t = 1'b0; #10
		t = 1'b1; #10
 		t = 1'b0; #10
		t = 1'b1; #10 $finish;
	end
endmodule

UCS614/q13.vcd
$date
	Wed Mar 21 11:34:36 2018
$end
$version
	Icarus Verilog
$end
$timescale
	1s
$end
$scope module test $end
$var wire 1 ! qbar $end
$var wire 1 " q $end
$var reg 1 # clk $end
$var reg 1 $ i $end
$var reg 1 % t $end
$scope module tff $end
$var wire 1 # clk $end
$var wire 1 % t $end
$var reg 1 " q $end
$var reg 1 ! qbar $end
$upscope $end
$upscope $end
$enddefinitions $end
#0
$dumpvars
0%
0$
0#
0"
1!
$end
#5
1$
1#
#10
0$
0#
1%
#15
0!
1"
1$
1#
#20
0$
0#
0%
#25
1$
1#
#30
0$
0#
1%
#35
1!
0"
1$
1#
#40
0$
0#
