UCS614/q14.v
// program for resetting D and T flip flops - async and sync
module DSyncReset(d, q, qbar, clk, reset);
	input d, clk, reset;
	output q, qbar;
	reg q, qbar;

	always @(posedge clk) begin
		if (reset)
			q = 0;
		else
			q = d;
		qbar = ~q;
	end
endmodule

module DASyncReset(d, q, qbar, clk, reset);
	input d, clk, reset;
	output q, qbar;
	reg q, qbar;

	always @(posedge clk or reset) begin
		if (reset)
			q = 0;
		else
			q = d;
		qbar = ~q;
	end
endmodule

module test;
	reg d, clk, reset, i;
	wire q, qbar;
	DASyncReset t(.d(d), .clk(clk), .reset(reset), .q(q), .qbar(qbar));

	initial begin
		clk = 0;
		for (i = 0; i < 16; i++)
			#5 clk = ~clk;
	end

	initial begin
		$dumpfile("q14.vcd");
		$dumpvars(0, test);
		$display("CLK\tD\tRST\tQ\tQbar");
		$monitor("%b\t%b\t%b\t%b\t%b", clk, d, reset, q, qbar);
			reset = 0; #2 d = 0; #2
			reset = 0; #2 d = 1; #2
			reset = 1; #2 d = 0; #2
			reset = 1; #2 d = 1; #2
			reset = 0; #2 d = 0; #2
			reset = 0; #2 d = 1; #2
			reset = 1; #2 d = 0; #2
			reset = 1; #2 d = 1; #2
		$finish;
	end
endmodule

UCS614/q14.vcd
$date
	Wed Apr 11 11:06:50 2018
$end
$version
	Icarus Verilog
$end
$timescale
	1s
$end
$scope module test $end
$var wire 1 ! qbar $end
$var wire 1 " q $end
$var reg 1 # clk $end
$var reg 1 $ d $end
$var reg 1 % i $end
$var reg 1 & reset $end
$scope module t $end
$var wire 1 # clk $end
$var wire 1 $ d $end
$var wire 1 & reset $end
$var reg 1 " q $end
$var reg 1 ! qbar $end
$upscope $end
$upscope $end
$enddefinitions $end
#0
$dumpvars
0&
0%
x$
0#
x"
x!
$end
#2
0$
#5
1!
0"
1%
1#
#6
1$
#8
1&
#10
0$
0%
0#
#14
1$
#15
1%
1#
#16
0!
1"
0&
#18
0$
#20
0%
0#
#22
1$
#24
1!
0"
1&
#25
1%
1#
#26
0$
#30
1$
0%
0#
