UCS614/q3b.v
module fullsubtractor(num1,num2,num3,diff,borrow);
	input num1, num2, num3;
	output diff, borrow;
	wire r1, r2, r3, r4, r5;
	assign r1 = ~num1;
	assign r2 = ~num2;
	assign r3 = ~num3;
	assign diff = (r1&r2&num3)|(r1&num2&r3)|(num1&r2&r3)|(num1&num2&num3);
	assign borrow = (r1&num3)|(r1&num2)|(num2&num3);
endmodule

module test;
	reg a,b,c;
	wire d,e;
	fullsubtractor fs(a,b,c,d,e);
	initial begin
		$dumpfile("q3b.vcd");
		$dumpvars(0,test);
		$display("a b c\td e");
		$monitor("%b %b %b\t%b %b", a,b,c,d,e);
		a=0; b=0; c=0; #10
		a=0; b=0; c=1; #10
		a=0; b=1; c=0; #10
		a=0; b=1; c=1; #10
		a=1; b=0; c=0; #10
		a=1; b=0; c=1; #10
		a=1; b=1; c=0; #10
		a=1; b=1; c=1; #10	$finish;
	end
endmodule

UCS614/q3b.vcd
$date
	Wed Mar 21 02:14:13 2018
$end
$version
	Icarus Verilog
$end
$timescale
	1s
$end
$scope module test $end
$var wire 1 ! e $end
$var wire 1 " d $end
$var reg 1 # a $end
$var reg 1 $ b $end
$var reg 1 % c $end
$scope module fs $end
$var wire 1 ! borrow $end
$var wire 1 " diff $end
$var wire 1 # num1 $end
$var wire 1 $ num2 $end
$var wire 1 % num3 $end
$var wire 1 & r1 $end
$var wire 1 ' r2 $end
$var wire 1 ( r3 $end
$upscope $end
$upscope $end
$enddefinitions $end
#0
$dumpvars
1(
1'
1&
0%
0$
0#
0"
0!
$end
#10
1"
1!
0(
1%
#20
1(
0'
0%
1$
#30
0"
0(
1%
#40
1"
0!
1(
1'
0&
0%
0$
1#
#50
0"
0(
1%
#60
1(
0'
0%
1$
#70
1"
1!
0(
1%
